qdev/__init__.py
qdev/cli.py
qdev-0.0.2.dist-info/METADATA
qdev-0.0.2.dist-info/WHEEL
qdev-0.0.2.dist-info/entry_points.txt
qdev-0.0.2.dist-info/top_level.txt
qdev-0.0.2.dist-info/RECORD
