Metadata-Version: 2.1
Name: qdev
Version: 0.0.2
Summary: An AI powered cli to make setting up a development environment fast and efficient.
Home-page: https://github.com/yourusername/my-cli-tool
Author: Your Name
Author-email: your.email@example.com
License: MIT
Classifier: Programming Language :: Python :: 3
Classifier: License :: OSI Approved :: MIT License
